TerminalColorNew/__init__.py
TerminalColorNew/main.py
terminalcolornew-0.0.3.dist-info/METADATA
terminalcolornew-0.0.3.dist-info/WHEEL
terminalcolornew-0.0.3.dist-info/top_level.txt
terminalcolornew-0.0.3.dist-info/RECORD
