Metadata-Version: 2.4
Name: TerminalColorNew
Version: 0.0.3
Summary: can change color of console output
Home-page: https://github.com/ZheniaNSK/TerminalColorNew
Author: buixobra
Author-email: evgenijsattorovphoto@gmail.com
Requires-Python: >=3.10
Requires-Dist: rich>=13.7.1
Dynamic: author
Dynamic: author-email
Dynamic: description
Dynamic: description-content-type
Dynamic: home-page
Dynamic: keywords
Dynamic: requires-dist
Dynamic: requires-python
Dynamic: summary
